rlime/__init__.py
rlime/arm.py
rlime/params.json
rlime/py.typed
rlime/rlime.py
rlime/rlime_anchor.py
rlime/rlime_lime.py
rlime/rlime_types.py
rlime/sampler.py
rlime/utils.py
rlime/datasets/adult/adult.data
rlime/datasets/lendingclub/._LoanStats3a.csv
rlime/datasets/lendingclub/._LoanStats3a.csv.zip
rlime/datasets/lendingclub/._LoanStats3a_securev1.csv
rlime/datasets/lendingclub/._LoanStats3a_securev1.csv.zip
rlime/datasets/lendingclub/LoanStats3a_securev1.csv
rlime/datasets/recidivism/._Data_1978.csv
rlime/datasets/recidivism/._Data_1980.csv
rlime/datasets/recidivism/._ICPSR_08987.zip
rlime/datasets/recidivism/._Recidivism-20161220T120033Z.zip
rlime/datasets/recidivism/Data_1980.csv
rlime-0.1.1.dist-info/METADATA
rlime-0.1.1.dist-info/WHEEL
rlime-0.1.1.dist-info/licenses/LICENSE
rlime-0.1.1.dist-info/RECORD
