Metadata-Version: 2.3
Name: rlime
Version: 0.1.1
Summary: Implementation of R-LIME, a novel method for interpreting the behavior of ML models.
License-File: LICENSE
Requires-Python: >=3.8
Requires-Dist: anchor-exp>=0.0.2.0
Requires-Dist: pandas>=2.2.2
Requires-Dist: river>=0.21.1
Requires-Dist: scikit-learn>=1.5.0
